{
  "updated_at": "2026-06-17T09:04:30.932518+00:00",
  "sport": [
    {
      "title": "Vor der Tour de Suisse – Alles dreht sich um Pogacar",
      "link": "https://www.srf.ch/sport/mehr-sport/rad/rad-strasse/vor-der-tour-de-suisse-alles-dreht-sich-um-pogacar",
      "published": "Tue, 16 Jun 2026 21:12:40 +0200",
      "source": "Sport News aus der Schweiz und International – Sport – SRF"
    },
    {
      "title": "Radsport in der Schweiz – Dieses neue Konzept soll die Tour de Suisse retten",
      "link": "https://www.srf.ch/news/schweiz/radsport-in-der-schweiz-dieses-neue-konzept-soll-die-tour-de-suisse-retten",
      "published": "Tue, 16 Jun 2026 17:25:24 +0200",
      "source": "Sport News aus der Schweiz und International – Sport – SRF"
    },
    {
      "title": "Messi, Mbappé, Haaland – «Gibt keine Worte mehr»: Superstars liefern an der WM",
      "link": "https://www.srf.ch/sport/fussball/fifa-wm-2026/messi-mbappe-haaland-gibt-keine-worte-mehr-superstars-liefern-an-der-wm",
      "published": "Wed, 17 Jun 2026 09:01:45 +0200",
      "source": "Sport News aus der Schweiz und International – Sport – SRF"
    },
    {
      "title": "Im WM-Spiel gegen Algerien – Messis Foul: Wäre ein Platzverweis angebracht gewesen?",
      "link": "https://www.srf.ch/sport/fussball/fifa-wm-2026/im-wm-spiel-gegen-algerien-messis-foul-waere-ein-platzverweis-angebracht-gewesen",
      "published": "Wed, 17 Jun 2026 10:25:17 +0200",
      "source": "Sport News aus der Schweiz und International – Sport – SRF"
    },
    {
      "title": "WM 2026: Gruppe J – Messi egalisiert mit Hattrick WM-Rekord – Argentinien siegt",
      "link": "https://www.srf.ch/sport/fussball/fifa-wm-2026/wm-2026-gruppe-j-messi-egalisiert-mit-hattrick-wm-rekord-argentinien-siegt",
      "published": "Wed, 17 Jun 2026 05:29:33 +0200",
      "source": "Sport News aus der Schweiz und International – Sport – SRF"
    },
    {
      "title": "WM 2026: Gruppe J – Österreich mogelt sich gegen Jordanien zum 1. WM-Sieg seit 1990",
      "link": "https://www.srf.ch/sport/fussball/fifa-wm-2026/wm-2026-gruppe-j-oesterreich-mogelt-sich-gegen-jordanien-zum-1-wm-sieg-seit-1990",
      "published": "Wed, 17 Jun 2026 08:32:27 +0200",
      "source": "Sport News aus der Schweiz und International – Sport – SRF"
    },
    {
      "title": "Im WM-Spiel gegen Algerien – Messis Foul: Wäre ein Platzverweis angebracht gewesen?",
      "link": "https://www.srf.ch/sport/fussball/fifa-wm-2026/im-wm-spiel-gegen-algerien-messis-foul-waere-ein-platzverweis-angebracht-gewesen",
      "published": "Wed, 17 Jun 2026 10:25:17 +0200",
      "source": "Fussball – News, Analysen & Highlights"
    },
    {
      "title": "Messi, Mbappé, Haaland – «Gibt keine Worte mehr»: Superstars liefern an der WM",
      "link": "https://www.srf.ch/sport/fussball/fifa-wm-2026/messi-mbappe-haaland-gibt-keine-worte-mehr-superstars-liefern-an-der-wm",
      "published": "Wed, 17 Jun 2026 09:01:45 +0200",
      "source": "Fussball – News, Analysen & Highlights"
    },
    {
      "title": "WM 2026: Gruppe J – Österreich mogelt sich gegen Jordanien zum 1. WM-Sieg seit 1990",
      "link": "https://www.srf.ch/sport/fussball/fifa-wm-2026/wm-2026-gruppe-j-oesterreich-mogelt-sich-gegen-jordanien-zum-1-wm-sieg-seit-1990",
      "published": "Wed, 17 Jun 2026 08:32:27 +0200",
      "source": "Fussball – News, Analysen & Highlights"
    },
    {
      "title": "WM 2026: Gruppe K – Portugal strebt nach dem Maximum – auch für Diogo Jota",
      "link": "https://www.srf.ch/sport/fussball/fifa-wm-2026/wm-2026-gruppe-k-portugal-strebt-nach-dem-maximum-auch-fuer-diogo-jota",
      "published": "Wed, 17 Jun 2026 08:25:18 +0200",
      "source": "Fussball – News, Analysen & Highlights"
    },
    {
      "title": "WM-Auftakt gegen Kroatien – England startet die Mission «2. Stern»",
      "link": "https://www.srf.ch/sport/fussball/fifa-wm-2026/wm-auftakt-gegen-kroatien-england-startet-die-mission-2-stern",
      "published": "Wed, 17 Jun 2026 08:24:04 +0200",
      "source": "Fussball – News, Analysen & Highlights"
    },
    {
      "title": "SRF-Programm in der Übersicht – Das läuft am Mittwoch an der FIFA WM 2026",
      "link": "https://www.srf.ch/sport/fussball/fifa-wm-2026/srf-programm-in-der-uebersicht-das-laeuft-am-mittwoch-an-der-fifa-wm-2026",
      "published": "Wed, 17 Jun 2026 08:23:23 +0200",
      "source": "Fussball – News, Analysen & Highlights"
    }
  ],
  "gaming": [
    {
      "title": "WoW Midnight: Offizielle Patch Notes zu Update 12.0.7 \"Enthüllungen\"",
      "link": "https://www.pcgames.de/World-of-Warcraft-Spiel-42971/Specials/WoW-Midnight-Offizielle-Patch-Notes-zu-Update-1207-Enthuellungen-1545530/",
      "published": "Wed, 17 Jun 2026 11:00:00 +0200",
      "source": "PCGames: Wissen, was gespielt wird!"
    },
    {
      "title": "Toy Story 5 steuert auf Milliarden-Erfolg zu, kassiert aber kuriosen Negativ-Rekord",
      "link": "https://www.pcgames.de/Pixar-Animation-Studios-Firma-208366/News/Toy-Story-5-Minus-Rekord-trotz-grossartiger-Prognosen-1545513/",
      "published": "Wed, 17 Jun 2026 10:30:00 +0200",
      "source": "PCGames: Wissen, was gespielt wird!"
    },
    {
      "title": "Microsoft Flight Simulator bekommt kostenlose Konkurrenz ... von Google Earth",
      "link": "https://www.pcgames.de/Microsoft-Flight-Simulator-2024-Spiel-74308/News/Google-bringt-eigenen-Flugsimulator-in-Earth-App-1545485/",
      "published": "Wed, 17 Jun 2026 10:00:00 +0200",
      "source": "PCGames: Wissen, was gespielt wird!"
    },
    {
      "title": "The Planet Crafter: Survival-Hit erscheint schon bald für PS5 und Xbox Series X/S",
      "link": "https://www.pcgames.de/The-Planet-Crafter-Spiel-73662/News/Gefeiertes-Survivalspiel-erscheint-fuer-Konsolen-1545512/",
      "published": "Wed, 17 Jun 2026 09:24:00 +0200",
      "source": "PCGames: Wissen, was gespielt wird!"
    },
    {
      "title": "Control Resonant: Mit dieser Strategie will Remedy im vollgestopften September brillieren",
      "link": "https://www.pcgames.de/Control-Resonant-Spiel-75469/News/Release-September-Kampagne-Remedy-1545462/",
      "published": "Wed, 17 Jun 2026 09:00:00 +0200",
      "source": "PCGames: Wissen, was gespielt wird!"
    },
    {
      "title": "Nach Peak und Lethal Company: Ein neuer Multiplayer-Hit erobert Steam",
      "link": "https://www.pcgames.de/Spiele-Thema-239104/News/Steam-Friendslop-Multiplayer-Koop-Meccha-Chameleon-1545449/",
      "published": "Wed, 17 Jun 2026 08:00:00 +0200",
      "source": "PCGames: Wissen, was gespielt wird!"
    }
  ]
}